LICENSE
README.md
setup.cfg
setup.py
imported/__init__.py
imported/decorators.py
imported/decorators_test_script.py
imported/imports.py
imported.egg-info/PKG-INFO
imported.egg-info/SOURCES.txt
imported.egg-info/dependency_links.txt
imported.egg-info/requires.txt
imported.egg-info/top_level.txt
tests/__init__.py
tests/conftest.py
tests/test_decorators.py
tests/test_imports.py